ura_token/__init__.py
ura_token/example.py
ura_token/ura_token.py
ura_token_pkg_chengguan-0.0.4.dist-info/LICENSE
ura_token_pkg_chengguan-0.0.4.dist-info/METADATA
ura_token_pkg_chengguan-0.0.4.dist-info/WHEEL
ura_token_pkg_chengguan-0.0.4.dist-info/top_level.txt
ura_token_pkg_chengguan-0.0.4.dist-info/RECORD
