Metadata-Version: 2.1
Name: ura-token-pkg-chengguan
Version: 0.0.4
Summary: A small example to obtain URA API token.
Home-page: https://github.com/chengguan/ura_token_package
Author: Teo Cheng Guan
Author-email: chengguan.teo@gmail.com
License: UNKNOWN
Project-URL: Bug Tracker, https://github.com/chengguan/ura_token_package/issues
Platform: UNKNOWN
Classifier: Programming Language :: Python :: 3
Classifier: License :: OSI Approved :: MIT License
Classifier: Operating System :: OS Independent
Requires-Python: >=3.6
License-File: LICENSE
